tap_playstore/__init__.py
tap_playstore/__main__.py
tap_playstore/client.py
tap_playstore/schemas/earnings.json
tap_playstore/schemas/play_balance_krw.json
tap_playstore/schemas/reviews.json
tap_playstore/schemas/sales_reports.json
tap_playstore/schemas/stats_by_dimension/buyers_7d.json
tap_playstore/schemas/stats_by_dimension/crashes.json
tap_playstore/schemas/stats_by_dimension/gcm.json
tap_playstore/schemas/stats_by_dimension/installs.json
tap_playstore/schemas/stats_by_dimension/ratings.json
tap_playstore/schemas/stats_by_dimension/retained_installers.json
tap_playstore/schemas/stats_overview/crashes.json
tap_playstore/schemas/stats_overview/gcm.json
tap_playstore/schemas/stats_overview/installs.json
tap_playstore/schemas/stats_overview/ratings.json
tap_playstore/schemas/store_performance_country.json
tap_playstore/schemas/store_performance_traffic_source.json
tap_playstore/schemas/subscriptions_country.json
tap_playstore/streams.py
tap_playstore/tap.py
tap_playstore-0.1.4.dist-info/LICENSE
tap_playstore-0.1.4.dist-info/METADATA
tap_playstore-0.1.4.dist-info/WHEEL
tap_playstore-0.1.4.dist-info/entry_points.txt
tap_playstore-0.1.4.dist-info/RECORD
