Metadata-Version: 2.1
Name: tap-playstore
Version: 0.1.4
Summary: `tap-playstore` is a Singer tap for Google PlayStore Console Reports, built with the Meltano Singer SDK.
License: Apache-2.0
Keywords: ELT,GooglePlayStoreConsole
Author: Haleemur Ali
Author-email: haleemur@gmail.com
Requires-Python: >=3.8,<3.13
Classifier: Intended Audience :: Developers
Classifier: License :: OSI Approved :: Apache Software License
Classifier: Operating System :: OS Independent
Classifier: Programming Language :: Python :: 3
Classifier: Programming Language :: Python :: 3.8
Classifier: Programming Language :: Python :: 3.9
Classifier: Programming Language :: Python :: 3.10
Classifier: Programming Language :: Python :: 3.11
Classifier: Programming Language :: Python :: 3.12
Provides-Extra: s3
Requires-Dist: fs-s3fs (>=1.1.1,<1.2.0) ; extra == "s3"
Requires-Dist: google-auth (>=2.28.1,<3.0.0)
Requires-Dist: google-cloud-storage (>=2.14.0,<3.0.0)
Requires-Dist: importlib-resources (==6.1.*) ; python_version < "3.9"
Requires-Dist: singer-sdk (>=0.35.2,<0.37.0)
